amazon_braket_schemas-1.29.0.dist-info/licenses/LICENSE
amazon_braket_schemas-1.29.0.dist-info/licenses/NOTICE
braket/_schemas/__init__.py
braket/_schemas/_version.py
braket/device_schema/__init__.py
braket/device_schema/blackbird_device_action_properties.py
braket/device_schema/continuous_variable_qpu_paradigm_properties_v1.py
braket/device_schema/device_action_properties.py
braket/device_schema/device_capabilities.py
braket/device_schema/device_connectivity.py
braket/device_schema/device_execution_window.py
braket/device_schema/device_service_properties_v1.py
braket/device_schema/gate_model_parameters_v1.py
braket/device_schema/gate_model_qpu_paradigm_properties_v1.py
braket/device_schema/jaqcd_device_action_properties.py
braket/device_schema/openqasm_device_action_properties.py
braket/device_schema/openqasm_program_set_device_action_properties.py
braket/device_schema/result_type.py
braket/device_schema/standardized_gate_model_qpu_device_properties_v1.py
braket/device_schema/standardized_gate_model_qpu_device_properties_v2.py
braket/device_schema/standardized_gate_model_qpu_device_properties_v3.py
braket/device_schema/aqt/__init__.py
braket/device_schema/aqt/aqt_device_capabilities_v1.py
braket/device_schema/aqt/aqt_provider_properties_v1.py
braket/device_schema/common/gate_model_device_parameters_v1.py
braket/device_schema/dwave/__init__.py
braket/device_schema/dwave/dwave_2000Q_device_level_parameters_v1.py
braket/device_schema/dwave/dwave_2000Q_device_parameters_v1.py
braket/device_schema/dwave/dwave_advantage_device_level_parameters_v1.py
braket/device_schema/dwave/dwave_advantage_device_parameters_v1.py
braket/device_schema/dwave/dwave_device_capabilities_v1.py
braket/device_schema/dwave/dwave_device_parameters_v1.py
braket/device_schema/dwave/dwave_provider_level_parameters_v1.py
braket/device_schema/dwave/dwave_provider_properties_v1.py
braket/device_schema/error_mitigation/__init__.py
braket/device_schema/error_mitigation/debias.py
braket/device_schema/error_mitigation/error_mitigation_properties.py
braket/device_schema/error_mitigation/error_mitigation_scheme.py
amazon_braket_schemas-1.29.0.dist-info/METADATA
amazon_braket_schemas-1.29.0.dist-info/WHEEL
amazon_braket_schemas-1.29.0.dist-info/top_level.txt
amazon_braket_schemas-1.29.0.dist-info/RECORD
